<?xml version='1.0' encoding='utf-8'?><m:page id='563c9caf-85ed-4f86-bd9a-4eb31f2f492b' xmlns='http://www.w3.org/1999/xhtml' title='Update model reflection' class='layout-sidebar-responsive' xmlns:m='http://schemas.mendix.com/forms/1.0'><m:layouts><m:layout path='SAML20/Full_Responsive.layout.xml'></m:layout><m:layout path='MyFirstModule/Layout.layout.xml'></m:layout></m:layouts><m:arguments><m:argument parameterName='1653f584-2057-420b-84ec-e9546e1be75b'><div data-mendix-id='16_0' data-mendix-type='mxui.widget.DataView' data-mendix-props='"friendlyId":"SAML20.SSOConfig_Step0.dataView1","entity":"SAML20.SSOConfiguration","schema":"7665e633-8b8f-4522-9d93-20ca34cef0a8","datasource":{"friendlyId":"SAML20.SSOConfig_Step0.dataView1","type":"direct","path":"SAML20.SSOConfiguration"}' class='mx-name-dataView1' tabindex='0'></div></m:argument></m:arguments><m:templates><m:template widget-id='16_0' name='content'><div data-mendix-id='16_1_2' class='mx-layoutgrid mx-layoutgrid-fluid container-fluid mx-name-layoutGrid1'><div class='row'><div class='col-md-2'><div class='mx-name-container2' style='margin-bottom: 20px;'><div data-mendix-id='16_1_6' data-mendix-type='mxui.widget.ReactWidgetWrapper' data-mendix-props='"widgetTree":[{"widget":"com.mendix.widget.core.Text","widgetId":"16_1_6","props":{"name":"label12","class":"mx-name-label12","style":{},"caption":{"$type":"DynamicTextProperty","template":{"elements":["Modules"],"friendlyId":"MxModelReflection.MxObjects.label12"}},"renderMode":"h3"}}]'></div><div data-mendix-id='16_1_7' data-mendix-type='mxui.widget.ReactWidgetWrapper' data-mendix-props='"widgetTree":[{"widget":"com.mendix.widget.core.ActionButton","widgetId":"16_1_7","props":{"name":"microflowButton7","class":"mx-name-microflowButton7","id":"16_1_7","style":{},"renderType":"button","buttonClass":"btn-primary","caption":{"$type":"DynamicTextProperty","template":{"elements":["Click to refresh"],"friendlyId":"MxModelReflection.MxObjects.microflowButton7"}},"tooltip":{"$type":"DynamicTextProperty","template":{"elements":[""]}},"icon":{"$type":"WebIconProperty","icon":{"type":"glyph","iconClass":"glyphicon-refresh"}},"action":{"$type":"ActionProperty","action":{"type":"callMicroflow","argMap":{},"config":{"name":"MxModelReflection.IVK_SyncObjects","async":true,"progress":{"message":"Synchronizing entities and microflows...","modal":true},"validate":"view","allowedRoles":["Administrator"]}},"abortOnServerValidation":true},"disabledDuringAction":false}}]' data-mendix-roles='Administrator'></div></div><div data-mendix-id='16_1_8' data-mendix-type='mxui.widget.ListView' data-mendix-props='"friendlyId":"MxModelReflection.MxObjects.listView1","hasSearch":false,"datasource":{"friendlyId":"MxModelReflection.MxObjects.listView1","type":"microflow","microflow":"MxModelReflection.DSL_Modules","path":"MxModelReflection.Module","queryId":"o35qvFjjYUKF5y7jAk3GWA","argMap":{}},"page":0,"selectable":"","action":{"type":"doNothing","argMap":{},"config":{}},"templateMap":{"MxModelReflection.Module":"MxModelReflection.Module"}' class='mx-name-listView1 listview-lined'></div></div><div class='col-md-10'><div class='mx-name-container3' style='margin-bottom: 20px;'><div data-mendix-id='16_1_11' data-mendix-type='mxui.widget.ReactWidgetWrapper' data-mendix-props='"widgetTree":[{"widget":"com.mendix.widget.core.Text","widgetId":"16_1_11","props":{"name":"label1","class":"mx-name-label1","style":{},"caption":{"$type":"DynamicTextProperty","template":{"elements":["Synchronize all entities and microflows of checked modules on the left"],"friendlyId":"MxModelReflection.MxObjects.label1"}},"renderMode":"h3"}}]'></div><div data-mendix-id='16_1_12' data-mendix-type='mxui.widget.ReactWidgetWrapper' data-mendix-props='"widgetTree":[{"widget":"com.mendix.widget.core.ActionButton","widgetId":"16_1_12","props":{"name":"microflowButton8","class":"mx-name-microflowButton8","id":"16_1_12","style":{},"renderType":"button","buttonClass":"btn-primary","caption":{"$type":"DynamicTextProperty","template":{"elements":["Click to refresh"],"friendlyId":"MxModelReflection.MxObjects.microflowButton8"}},"tooltip":{"$type":"DynamicTextProperty","template":{"elements":[""]}},"icon":{"$type":"WebIconProperty","icon":{"type":"glyph","iconClass":"glyphicon-refresh"}},"action":{"$type":"ActionProperty","action":{"type":"callMicroflow","argMap":{},"config":{"name":"MxModelReflection.IVK_SyncObjects","async":true,"progress":{"message":"Synchronizing entities and microflows...","modal":true},"validate":"view","allowedRoles":["Administrator"]}},"abortOnServerValidation":true},"disabledDuringAction":false}}]' data-mendix-roles='Administrator'></div></div><div data-mendix-id='16_1_13' data-mendix-type='mxui.widget.TabContainer' data-mendix-props='"friendlyId":"MxModelReflection.MxObjects.tabControl1"' class='mx-name-tabControl1' style='margin-top: 10px;' tabindex='0'></div></div></div></div></m:template><m:template widget-id='16_0' name='footer'><div data-mendix-id='16_43' data-mendix-type='mxui.widget.ReactWidgetWrapper' data-mendix-props='"widgetTree":[{"widget":"com.mendix.widget.core.ActionButton","widgetId":"16_43","props":{"name":"microflowButton1","class":"mx-name-microflowButton1","id":"16_43","style":{},"renderType":"button","buttonClass":"btn-primary","caption":{"$type":"DynamicTextProperty","template":{"elements":["Next"],"friendlyId":"SAML20.SSOConfig_Step0.microflowButton1"}},"tooltip":{"$type":"DynamicTextProperty","template":{"elements":[""]}},"icon":null,"action":{"$type":"ActionProperty","action":{"type":"callMicroflow","argMap":{"SSOConfiguration":{"widget":"$pageParameter","source":"object"}},"config":{"name":"SAML20.SSOConfig_ToStep1","validate":"view","allowedRoles":["Administrator"]}},"abortOnServerValidation":true},"disabledDuringAction":false}}]' data-mendix-roles='Administrator'></div><div data-mendix-id='16_44' data-mendix-type='mxui.widget.ReactWidgetWrapper' data-mendix-props='"widgetTree":[{"widget":"com.mendix.widget.core.ActionButton","widgetId":"16_44","props":{"name":"cancelButton1","class":"mx-name-cancelButton1","id":"16_44","style":{},"renderType":"button","buttonClass":"btn-default","caption":{"$type":"DynamicTextProperty","template":{"elements":["Cancel"],"friendlyId":"SAML20.SSOConfig_Step0.cancelButton1"}},"tooltip":{"$type":"DynamicTextProperty","template":{"elements":[""]}},"icon":null,"action":{"$type":"ActionProperty","action":{"type":"cancelChanges","argMap":{},"config":{"closePage":true}},"abortOnServerValidation":true},"disabledDuringAction":true}}]'></div></m:template><m:template widget-id='16_1_8' name='MxModelReflection.Module'><div data-mendix-id='16_1_45' data-mendix-type='mxui.widget.DataView' data-mendix-props='"friendlyId":"MxModelReflection.MxObjects.listView1","entity":"MxModelReflection.Module","schema":"d44f5b71-68e3-4327-85dc-c80b0308e009","datasource":{"friendlyId":"MxModelReflection.MxObjects.listView1","type":"direct","path":"MxModelReflection.Module"}' tabindex='0'></div></m:template><m:template widget-id='16_1_13' name='pages'><div data-mendix-id='16_1_14' data-mendix-type='mxui.widget.TabContent' data-mendix-props='"title":"Entities","delayLoading":false,"tabName":"tabPage1"'></div><div data-mendix-id='16_1_29' data-mendix-type='mxui.widget.TabContent' data-mendix-props='"title":"Microflows","delayLoading":true,"tabName":"tabPage2"'></div></m:template><m:template widget-id='16_1_45' name='content'><div data-mendix-id='16_1_46' data-mendix-type='mxui.widget.BoolSelect' data-mendix-props='"friendlyId":"MxModelReflection.MxObjects.checkBox1","insideFormGroup":false,"attributePath":"MxModelReflection.Module/SynchronizeObjectsWithinModule","readOnlyStyle":"text","validation":null,"events":{"change":{"type":"callMicroflow","argMap":{"Module":{"widget":"16_1_8","source":"object"}},"config":{"name":"MxModelReflection.IVK_ToggleModule","validate":"view","allowedRoles":["Administrator"]}},"focus":{"type":"doNothing","argMap":{},"config":{}},"blur":{"type":"doNothing","argMap":{},"config":{}}}' class='mx-name-checkBox1' style='display: inline-block;' tabindex='0'></div><div data-mendix-id='16_1_47' class='mx-name-textBox1' style='margin-left: 10px;display: inline-block;padding-top: 8px;'><div data-mendix-id='16_1_48' data-mendix-type='mxui.widget.TextInput' data-mendix-props='"friendlyId":"MxModelReflection.MxObjects.textBox1","readOnly":true,"insideFormGroup":false,"attributePath":"MxModelReflection.Module/ModuleName","readOnlyStyle":"text","validation":null,"events":{"change":{"type":"doNothing","argMap":{},"config":{}},"focus":{"type":"doNothing","argMap":{},"config":{}},"blur":{"type":"doNothing","argMap":{},"config":{}}},"placeholder":"","maxLength":200' tabindex='0'></div></div></m:template><m:template widget-id='16_1_14' name='content'><div data-mendix-id='16_1_15' class='mx-layoutgrid mx-layoutgrid-fluid mx-name-layoutGrid2'><div class='row'><div class='col-md-3'><div data-mendix-id='16_1_18' data-mendix-type='mxui.widget.TemplateGrid' data-mendix-props='"friendlyId":"MxModelReflection.MxObjects.templateGrid1","contextname":"16_1_18","entity":"MxModelReflection.MxObjectType","schema":"5763073a-91cc-478e-9dce-f132ab754beb","config":{"locale":"en_US","gridType":"Standalone","gridpresentation":{"rows":10,"columns":1,"controlbar":true,"pagingbar":true,"sortparams":[["CompleteName","asc"]],"searchbar":true,"waitforsearch":false,"selectionmode":"single","editable":false,"sortable":true,"refresh":0,"selectfirst":true},"datasource":{"friendlyId":"MxModelReflection.MxObjects.templateGrid1","type":"xpath","path":"MxModelReflection.MxObjectType"},"searchOptions":{"searchBar":true,"toggleable":false,"toggledByDefault":false},"searchElements":[{"searchInputName":"searchField10","defaults":null,"defaultsParser":"Simple","caption":"Module","path":"Module","operator":"contains"},{"searchInputName":"searchField9","defaults":null,"defaultsParser":"Simple","caption":"Entity","path":"Name","operator":"contains"},{"searchInputName":"searchField12","defaults":null,"defaultsParser":"Simple","caption":"Persistence type","path":"PersistenceType","operator":"=","retriever":"Enum"}],"controlBar":{"gridTools":[],"gridActions":[]},"plugins":{}}' class='mx-templategrid mx-name-templateGrid1' tabindex='0'></div></div><div class='col-md-9'><div data-mendix-id='16_1_27' data-mendix-type='mxui.widget.GroupBox' data-mendix-props='"friendlyId":"MxModelReflection.MxObjects.groupBox1","collapsable":true,"collapsed":false' class='mx-groupbox mx-groupbox-collapsible mx-name-groupBox1'><h2 class='mx-groupbox-header'><i class='glyphicon mx-groupbox-collapse-icon'></i>Entity details</h2><div class='mx-groupbox-body'><div data-mendix-id='16_1_28' data-mendix-type='mxui.widget.DataView' data-mendix-props='"friendlyId":"MxModelReflection.MxObjects.dataView1","entity":"MxModelReflection.MxObjectType","schema":"527b7df3-9250-4125-95b9-0163a1629f08","noEntityMessage":"Please select an entity to view it&apos;s details","datasource":{"friendlyId":"MxModelReflection.MxObjects.dataView1","type":"listen","contextsource":"16_1_18"}' class='mx-name-dataView1 form-horizontal' tabindex='0'></div></div></div></div></div></div></m:template><m:template widget-id='16_1_29' name='content'><div data-mendix-id='16_1_30' class='mx-layoutgrid mx-layoutgrid-fluid mx-name-layoutGrid4'><div class='row'><div class='col-md-3'><div data-mendix-id='16_1_33' data-mendix-type='mxui.widget.TemplateGrid' data-mendix-props='"friendlyId":"MxModelReflection.MxObjects.templateGrid2","contextname":"16_1_33","entity":"MxModelReflection.Microflows","schema":"20a20340-16af-4b1a-8038-52e9f4727b20","config":{"locale":"en_US","gridType":"Standalone","gridpresentation":{"rows":10,"columns":1,"controlbar":true,"pagingbar":true,"sortparams":[["CompleteName","asc"]],"searchbar":true,"waitforsearch":false,"selectionmode":"single","editable":false,"sortable":true,"refresh":0,"selectfirst":true},"datasource":{"friendlyId":"MxModelReflection.MxObjects.templateGrid2","type":"xpath","path":"MxModelReflection.Microflows"},"searchOptions":{"searchBar":true,"toggleable":false,"toggledByDefault":false},"searchElements":[{"searchInputName":"searchField11","defaults":null,"defaultsParser":"Simple","caption":"Module","path":"MxModelReflection.Microflows_Module/MxModelReflection.Module/ModuleName","operator":"=","datasource":{"type":"xpath","params":{"sort":[["ModuleName","asc"]]}}},{"searchInputName":"searchField13","defaults":null,"defaultsParser":"Simple","caption":"Name","path":"Name","operator":"contains"}],"controlBar":{"gridTools":[],"gridActions":[]},"plugins":{}}' class='mx-templategrid mx-name-templateGrid2' tabindex='0'></div></div><div class='col-md-9'><div data-mendix-id='16_1_41' data-mendix-type='mxui.widget.GroupBox' data-mendix-props='"friendlyId":"MxModelReflection.MxObjects.groupBox2","collapsable":true,"collapsed":false' class='mx-groupbox mx-groupbox-collapsible mx-name-groupBox2'><h2 class='mx-groupbox-header'><i class='glyphicon mx-groupbox-collapse-icon'></i>Entity details</h2><div class='mx-groupbox-body'><div data-mendix-id='16_1_42' data-mendix-type='mxui.widget.DataView' data-mendix-props='"friendlyId":"MxModelReflection.MxObjects.dataView3","entity":"MxModelReflection.Microflows","schema":"930e8999-7199-42b3-9ede-cc826cf32ebf","noEntityMessage":"Please select an entity to view it&apos;s details","datasource":{"friendlyId":"MxModelReflection.MxObjects.dataView3","type":"listen","contextsource":"16_1_33"}' class='mx-name-dataView3 form-horizontal' tabindex='0'></div></div></div></div></div></div></m:template><m:template widget-id='16_1_18' name='content'><div data-mendix-id='16_1_97' data-mendix-type='mxui.widget.DataView' data-mendix-props='"friendlyId":"MxModelReflection.MxObjects.templateGrid1","entity":"MxModelReflection.MxObjectType","schema":"64508125-82b8-49d4-a79d-e8101421be82","readOnly":true,"datasource":{"friendlyId":"MxModelReflection.MxObjects.templateGrid1","type":"direct","path":"MxModelReflection.MxObjectType"}' tabindex='0'></div></m:template><m:template widget-id='16_1_28' name='content'><div class='mx-name-container1 form-group'><label class='mx-name-label4 control-label col-sm-3' data-mendix-id='16_1_50'>Friendly name</label><div data-mendix-id='16_1_51' class='mx-name-textBox2 col-sm-6'><div data-mendix-id='16_1_102' data-mendix-type='mxui.widget.TextInput' data-mendix-props='"friendlyId":"MxModelReflection.MxObjects.textBox2","insideFormGroup":false,"attributePath":"MxModelReflection.MxObjectType/ReadableName","readOnlyStyle":"text","validation":null,"events":{"change":{"type":"doNothing","argMap":{},"config":{}},"focus":{"type":"doNothing","argMap":{},"config":{}},"blur":{"type":"doNothing","argMap":{},"config":{}}},"placeholder":"","maxLength":400' tabindex='0'></div></div><div class='mx-name-container4 col-sm-3'><div data-mendix-id='16_1_53' data-mendix-type='mxui.widget.ReactWidgetWrapper' data-mendix-props='"widgetTree":[{"widget":"com.mendix.widget.core.ActionButton","widgetId":"16_1_53","props":{"name":"microflowButton1","class":"mx-name-microflowButton1","id":"16_1_53","style":{},"renderType":"button","buttonClass":"btn-primary","caption":{"$type":"DynamicTextProperty","template":{"elements":["Save"],"friendlyId":"MxModelReflection.MxObjects.microflowButton1"}},"tooltip":{"$type":"DynamicTextProperty","template":{"elements":[""]}},"icon":null,"action":{"$type":"ActionProperty","action":{"type":"callMicroflow","argMap":{"MxObjectType":{"widget":"16_1_28","source":"object"}},"config":{"name":"MxModelReflection.IVK_MxObjectTypeCommit","async":true,"progress":{"message":"Saving...","modal":false},"validate":"view","allowedRoles":["Administrator"]}},"abortOnServerValidation":true},"disabledDuringAction":false}}]' data-mendix-roles='Administrator'></div></div></div><div data-mendix-id='16_1_54' class='mx-layoutgrid mx-layoutgrid-fluid mx-name-layoutGrid3'><div class='row'><div class='col-md-6'><div data-mendix-id='16_1_57' class='form-group mx-name-textBox10'><div data-mendix-id='16_1_103' data-mendix-type='mxui.widget.ReactWidgetWrapper' data-mendix-props='"widgetTree":[{"widget":"com.mendix.widget.core.Label","widgetId":"16_1_103","props":{"name":"","class":"control-label col-sm-3","caption":{"$type":"DynamicTextProperty","template":{"elements":["Name"],"friendlyId":"MxModelReflection.MxObjects."}}}}]'></div><div data-mendix-id='16_1_104' data-mendix-type='mxui.widget.TextInput' data-mendix-props='"friendlyId":"MxModelReflection.MxObjects.textBox10","readOnly":true,"insideFormGroup":true,"attributePath":"MxModelReflection.MxObjectType/Name","readOnlyStyle":"text","validation":null,"events":{"change":{"type":"doNothing","argMap":{},"config":{}},"focus":{"type":"doNothing","argMap":{},"config":{}},"blur":{"type":"doNothing","argMap":{},"config":{}}},"placeholder":"","maxLength":200' class='col-sm-9' tabindex='0'></div></div><div data-mendix-id='16_1_58' class='form-group mx-name-dropDown2'><div data-mendix-id='16_1_105' data-mendix-type='mxui.widget.ReactWidgetWrapper' data-mendix-props='"widgetTree":[{"widget":"com.mendix.widget.core.Label","widgetId":"16_1_105","props":{"name":"","class":"control-label col-sm-3","caption":{"$type":"DynamicTextProperty","template":{"elements":["Persistence"],"friendlyId":"MxModelReflection.MxObjects."}}}}]'></div><div data-mendix-id='16_1_106' data-mendix-type='mxui.widget.EnumSelect' data-mendix-props='"friendlyId":"MxModelReflection.MxObjects.dropDown2","readOnly":true,"insideFormGroup":true,"attributePath":"MxModelReflection.MxObjectType/PersistenceType","readOnlyStyle":"text","validation":null,"events":{"change":{"type":"doNothing","argMap":{},"config":{}},"focus":{"type":"doNothing","argMap":{},"config":{}},"blur":{"type":"doNothing","argMap":{},"config":{}}},"emptyOptionCaption":""' class='col-sm-9' tabindex='0'></div></div></div><div class='col-md-6'><div class='mx-name-container9 form-group'><label class='mx-name-label3 control-label col-sm-3' data-mendix-id='16_1_61'>Inherits from</label><div data-mendix-id='16_1_62' data-mendix-type='mxui.widget.DataView' data-mendix-props='"friendlyId":"MxModelReflection.MxObjects.dataView2","entity":"MxModelReflection.InheritsFromContainer","schema":"4ab91831-dc56-475a-b640-239ad8c8441c","datasource":{"friendlyId":"MxModelReflection.MxObjects.dataView2","type":"microflow","microflow":"MxModelReflection.DSO_InheritsFromContainer","path":"MxModelReflection.InheritsFromContainer","queryId":"RbXT/AmmsEOuYF8iRoCwqw","argMap":{"MxObjectType":{"widget":"16_1_28","source":"object"}}}' class='mx-name-dataView2 col-sm-9' tabindex='0'></div></div></div></div></div><div data-mendix-id='16_1_63' data-mendix-type='mxui.widget.TabContainer' data-mendix-props='"friendlyId":"MxModelReflection.MxObjects.tabControl2"' class='mx-name-tabControl2' tabindex='0'></div></m:template><m:template widget-id='16_1_33' name='content'><div data-mendix-id='16_1_108' data-mendix-type='mxui.widget.DataView' data-mendix-props='"friendlyId":"MxModelReflection.MxObjects.templateGrid2","entity":"MxModelReflection.Microflows","schema":"627512d5-1bf8-4ed1-b3fc-f48784a5fde7","readOnly":true,"datasource":{"friendlyId":"MxModelReflection.MxObjects.templateGrid2","type":"direct","path":"MxModelReflection.Microflows"}' tabindex='0'></div></m:template><m:template widget-id='16_1_42' name='content'><div data-mendix-id='16_1_82' class='form-group mx-name-textBox9'><div data-mendix-id='16_1_113' data-mendix-type='mxui.widget.ReactWidgetWrapper' data-mendix-props='"widgetTree":[{"widget":"com.mendix.widget.core.Label","widgetId":"16_1_113","props":{"name":"","class":"control-label col-sm-3","caption":{"$type":"DynamicTextProperty","template":{"elements":["Microflow name"],"friendlyId":"MxModelReflection.MxObjects."}}}}]'></div><div data-mendix-id='16_1_114' data-mendix-type='mxui.widget.TextInput' data-mendix-props='"friendlyId":"MxModelReflection.MxObjects.textBox9","readOnly":true,"insideFormGroup":true,"attributePath":"MxModelReflection.Microflows/CompleteName","readOnlyStyle":"text","validation":null,"events":{"change":{"type":"doNothing","argMap":{},"config":{}},"focus":{"type":"doNothing","argMap":{},"config":{}},"blur":{"type":"doNothing","argMap":{},"config":{}}},"placeholder":"","maxLength":200' class='col-sm-9' tabindex='0'></div></div><div class='mx-name-container7 form-group'><label class='mx-name-label6 control-label col-sm-3' data-mendix-id='16_1_84'>Input parameters</label><div data-mendix-id='16_1_85' data-mendix-type='mxui.widget.ReferenceSetSelector' data-mendix-props='"friendlyId":"MxModelReflection.MxObjects.referenceSetSelector1","entity":"MxModelReflection.Parameter","schema":"e0702780-61dd-4b8e-ac9f-f409afd49f8a","config":{"locale":"en_US","gridType":"Standalone","gridpresentation":{"rows":5,"columns":1,"controlbar":true,"pagingbar":true,"sortparams":[["Name","asc"]],"searchbar":false,"waitforsearch":false,"selectionmode":"none","editable":false,"sortable":true,"selectfirst":false,"showemptyrows":false},"datasource":{"friendlyId":"MxModelReflection.MxObjects.referenceSetSelector1","type":"referenceSet","entity":"MxModelReflection.Parameter","reference":"MxModelReflection.Microflows_InputParameter"},"controlBar":{"gridTools":[],"gridActions":[]},"griddata":[{"tag":"Name","name":"column5","editable":false,"render":"String","display":{"width":"32%","string":"Name"}},{"tag":"MxModelReflection.Parameter_ValueType/MxModelReflection.ValueType/Name","name":"column6","editable":false,"render":"String","display":{"width":"34%","string":"Primitive type"}},{"tag":"MxModelReflection.Parameter_MxObjectType/MxModelReflection.MxObjectType/CompleteName","name":"column11","editable":false,"render":"String","display":{"width":"34%","string":"Objecttype"}}],"plugins":{}},"constrainedBy":[],"events":{"change":{"type":"doNothing","argMap":{},"config":{}}}' class='mx-referencesetselector mx-name-referenceSetSelector1 col-sm-9' tabindex='0'></div></div><div class='mx-name-container8 form-group'><label class='mx-name-label7 control-label col-sm-3' data-mendix-id='16_1_93'>Output</label><div class='mx-name-container10 col-sm-9'><div data-mendix-id='16_1_95' data-mendix-type='mxui.widget.ReferenceSelector' data-mendix-props='"friendlyId":"MxModelReflection.MxObjects.referenceSelector1","readOnly":true,"insideFormGroup":false,"attributePath":"MxModelReflection.Microflows/MxModelReflection.Microflows_Output_Type/MxModelReflection.ValueType/Name","readOnlyStyle":"text","attributePath":"MxModelReflection.Microflows/MxModelReflection.Microflows_Output_Type/MxModelReflection.ValueType/Name","datasource":{"friendlyId":"MxModelReflection.MxObjects.referenceSelector1","type":"xpath","path":"MxModelReflection.ValueType","constrainedBy":[],"sort":[["Name","asc"]]},"events":{"change":{"type":"doNothing","argMap":{},"config":{}}},"validation":null,"renderMode":"Drop-down","emptyOptionCaption":""' class='mx-name-referenceSelector1' tabindex='0'></div><div data-mendix-id='16_1_96' data-mendix-type='mxui.widget.ReferenceSelector' data-mendix-props='"friendlyId":"MxModelReflection.MxObjects.referenceSelector2","readOnly":true,"insideFormGroup":false,"attributePath":"MxModelReflection.Microflows/MxModelReflection.Microflows_Output_Type/MxModelReflection.ValueType/TypeEnum","readOnlyStyle":"text","attributePath":"MxModelReflection.Microflows/MxModelReflection.Microflows_Output_Type/MxModelReflection.ValueType/TypeEnum","datasource":{"friendlyId":"MxModelReflection.MxObjects.referenceSelector2","type":"xpath","path":"MxModelReflection.ValueType","constrainedBy":[],"sort":[["TypeEnum","asc"]]},"events":{"change":{"type":"doNothing","argMap":{},"config":{}}},"validation":null,"renderMode":"Drop-down","emptyOptionCaption":""' class='mx-name-referenceSelector2' tabindex='0'></div></div></div></m:template><m:template widget-id='16_1_97' name='content'><div class='mx-name-container5'><div data-mendix-id='16_1_99' class='mx-name-textBox4' style='display:inline;'><div data-mendix-id='16_1_115' data-mendix-type='mxui.widget.TextInput' data-mendix-props='"friendlyId":"MxModelReflection.MxObjects.textBox4","insideFormGroup":false,"attributePath":"MxModelReflection.MxObjectType/Module","readOnlyStyle":"text","validation":null,"events":{"change":{"type":"doNothing","argMap":{},"config":{}},"focus":{"type":"doNothing","argMap":{},"config":{}},"blur":{"type":"doNothing","argMap":{},"config":{}}},"placeholder":"","maxLength":200' tabindex='0'></div></div><label class='mx-name-label2' data-mendix-id='16_1_100'>.</label><div data-mendix-id='16_1_101' class='mx-name-textBox3' style='display:inline; font-weight: bold;'><div data-mendix-id='16_1_116' data-mendix-type='mxui.widget.TextInput' data-mendix-props='"friendlyId":"MxModelReflection.MxObjects.textBox3","insideFormGroup":false,"attributePath":"MxModelReflection.MxObjectType/Name","readOnlyStyle":"text","validation":null,"events":{"change":{"type":"doNothing","argMap":{},"config":{}},"focus":{"type":"doNothing","argMap":{},"config":{}},"blur":{"type":"doNothing","argMap":{},"config":{}}},"placeholder":"","maxLength":200' tabindex='0'></div></div></div></m:template><m:template widget-id='16_1_62' name='content'><div data-mendix-id='16_1_107' class='mx-name-textBox6'><div data-mendix-id='16_1_117' data-mendix-type='mxui.widget.TextInput' data-mendix-props='"friendlyId":"MxModelReflection.MxObjects.textBox6","readOnly":true,"insideFormGroup":false,"attributePath":"MxModelReflection.InheritsFromContainer/Summary","readOnlyStyle":"text","validation":null,"events":{"change":{"type":"doNothing","argMap":{},"config":{}},"focus":{"type":"doNothing","argMap":{},"config":{}},"blur":{"type":"doNothing","argMap":{},"config":{}}},"placeholder":""' tabindex='0'></div></div></m:template><m:template widget-id='16_1_63' name='pages'><div data-mendix-id='16_1_64' data-mendix-type='mxui.widget.TabContent' data-mendix-props='"title":"Attributes","delayLoading":false,"tabName":"tabPage3"'></div><div data-mendix-id='16_1_74' data-mendix-type='mxui.widget.TabContent' data-mendix-props='"title":"References","delayLoading":true,"tabName":"tabPage4"'></div></m:template><m:template widget-id='16_1_108' name='content'><div class='mx-name-container6'><div data-mendix-id='16_1_110' class='mx-name-textBox5' style='display:inline;'><div data-mendix-id='16_1_118' data-mendix-type='mxui.widget.TextInput' data-mendix-props='"friendlyId":"MxModelReflection.MxObjects.textBox5","insideFormGroup":false,"attributePath":"MxModelReflection.Microflows/Module","readOnlyStyle":"text","validation":null,"events":{"change":{"type":"doNothing","argMap":{},"config":{}},"focus":{"type":"doNothing","argMap":{},"config":{}},"blur":{"type":"doNothing","argMap":{},"config":{}}},"placeholder":"","maxLength":200' tabindex='0'></div></div><label class='mx-name-label5' data-mendix-id='16_1_111'>.</label><div data-mendix-id='16_1_112' class='mx-name-textBox7' style='display:inline; font-weight: bold;'><div data-mendix-id='16_1_119' data-mendix-type='mxui.widget.TextInput' data-mendix-props='"friendlyId":"MxModelReflection.MxObjects.textBox7","insideFormGroup":false,"attributePath":"MxModelReflection.Microflows/Name","readOnlyStyle":"text","validation":null,"events":{"change":{"type":"doNothing","argMap":{},"config":{}},"focus":{"type":"doNothing","argMap":{},"config":{}},"blur":{"type":"doNothing","argMap":{},"config":{}}},"placeholder":"","maxLength":200' tabindex='0'></div></div></div></m:template><m:template widget-id='16_1_64' name='content'><div data-mendix-id='16_1_65' data-mendix-type='mxui.widget.DataGrid' data-mendix-props='"friendlyId":"MxModelReflection.MxObjects.grid1","entity":"MxModelReflection.MxObjectMember","schema":"70bea9fc-09b9-4647-b147-22ae084fba93","config":{"locale":"en_US","gridType":"Standalone","gridpresentation":{"rows":10,"columns":1,"controlbar":true,"pagingbar":true,"sortparams":[["AttributeName","asc"]],"searchbar":true,"waitforsearch":false,"selectionmode":"single","editable":false,"sortable":true,"refresh":0,"selectfirst":false,"showemptyrows":false},"datasource":{"friendlyId":"MxModelReflection.MxObjects.grid1","type":"xpath","path":"MxModelReflection.MxObjectMember_MxObjectType/MxModelReflection.MxObjectMember"},"searchOptions":{"searchBar":true,"toggleable":false,"toggledByDefault":false},"searchElements":[{"searchInputName":"searchField1","defaults":null,"defaultsParser":"Simple","caption":"Member name","path":"AttributeName","operator":"contains"},{"searchInputName":"searchField2","defaults":null,"defaultsParser":"Simple","caption":"Type","path":"AttributeTypeEnum","operator":"=","retriever":"Enum"}],"controlBar":{"gridTools":[{"mxid":"16_1_69","friendlyId":"MxModelReflection.MxObjects.editButton1","name":"editButton1","caption":{"elements":["View"],"friendlyId":"MxModelReflection.MxObjects.editButton1"},"title":"","cssClass":"btn-primary","visibleForRoles":["Administrator"]}],"gridActions":[{"keyValue":"16_1_69","gridFunction":"InvokeAction","params":{"action":{"type":"openPage","argMap":{"$pageParameter":{"widget":"16_1_65","source":"selection"}},"config":{"name":"MxModelReflection/Member_View.page.xml","title":"View the attribute","location":"popup","resizable":true,"allowedRoles":["Administrator"],"specializations":{"MxModelReflection.MxObjectEnum":{"name":"MxModelReflection/MemberEnum_View.page.xml","title":"View the enum details","location":"popup","resizable":true}}}},"maintainSelection":true}}]},"defaultButton":{"clickType":"double","mxid":"16_1_69"},"griddata":[{"tag":"AttributeName","name":"column2","editable":false,"render":"String","display":{"width":"25%","string":"Member name"}},{"tag":"AttributeTypeEnum","name":"column3","editable":false,"render":"Enum","display":{"width":"75%","string":"Type"}}],"plugins":{}}' class='mx-datagrid mx-name-grid1' tabindex='0'></div></m:template><m:template widget-id='16_1_74' name='content'><div data-mendix-id='16_1_75' data-mendix-type='mxui.widget.DataGrid' data-mendix-props='"friendlyId":"MxModelReflection.MxObjects.grid2","entity":"MxModelReflection.MxObjectReference","schema":"6bb33997-e6db-49e5-bd8a-93532a78ec43","config":{"locale":"en_US","gridType":"Standalone","gridpresentation":{"rows":20,"columns":1,"controlbar":true,"pagingbar":true,"sortparams":[["CompleteName","asc"]],"searchbar":false,"waitforsearch":false,"selectionmode":"single","editable":false,"sortable":true,"refresh":0,"selectfirst":false,"showemptyrows":false},"datasource":{"friendlyId":"MxModelReflection.MxObjects.grid2","type":"xpath","path":"MxModelReflection.MxObjectReference","constraint":"[MxModelReflection.MxObjectReference_MxObjectType = &apos;[%CurrentObject%]&apos;]"},"controlBar":{"gridTools":[{"mxid":"16_1_79","friendlyId":"MxModelReflection.MxObjects.editButton3","name":"editButton3","caption":{"elements":["View"],"friendlyId":"MxModelReflection.MxObjects.editButton3"},"title":"","cssClass":"btn-primary","visibleForRoles":["Administrator"]}],"gridActions":[{"keyValue":"16_1_79","gridFunction":"InvokeAction","params":{"action":{"type":"openPage","argMap":{"$pageParameter":{"widget":"16_1_75","source":"selection"}},"config":{"name":"MxModelReflection/MxObjectReference_View.page.xml","location":"popup","resizable":true,"allowedRoles":["Administrator"]}},"maintainSelection":true}}]},"griddata":[{"tag":"CompleteName","name":"column1","editable":false,"render":"String","display":{"width":"50%","string":"Entity"}},{"tag":"MxModelReflection.MxObjectReference_MxObjectType/MxModelReflection.MxObjectType/CompleteName","name":"column4","editable":false,"render":"String","display":{"width":"50%","string":"Path"}}],"plugins":{}}' class='mx-datagrid mx-name-grid2' tabindex='0'></div></m:template></m:templates></m:page>